recipe_urls/.DS_Store
recipe_urls/__init__.py
recipe_urls/_abstract.py
recipe_urls/_utils.py
recipe_urls/abuelascounter.py
recipe_urls/acouplecooks.py
recipe_urls/addapinch.py
recipe_urls/afghankitchenrecipes.py
recipe_urls/allrecipes.py
recipe_urls/ambitiouskitchen.py
recipe_urls/archanaskitchen.py
recipe_urls/averiecooks.py
recipe_urls/bakingmischief.py
recipe_urls/bakingsense.py
recipe_urls/barefootcontessa.py
recipe_urls/bbc.py
recipe_urls/bettycrocker.py
recipe_urls/bigoven.py
recipe_urls/bluejeanchef.py
recipe_urls/bonappetit.py
recipe_urls/bongeats.py
recipe_urls/bowlofdelicious.py
recipe_urls/budgetbytes.py
recipe_urls/carlsbadcravings.py
recipe_urls/castironketo.py
recipe_urls/cdkitchen.py
recipe_urls/chefsavvy.py
recipe_urls/closetcooking.py
recipe_urls/cookieandkate.py
recipe_urls/copykat.py
recipe_urls/countryliving.py
recipe_urls/creativecanning.py
recipe_urls/davidlebovitz.py
recipe_urls/delish.py
recipe_urls/domesticateme.py
recipe_urls/downshiftology.py
recipe_urls/eatingbirdfood.py
recipe_urls/eatingwell.py
recipe_urls/eatliverun.py
recipe_urls/eatsmarter.py
recipe_urls/eatwell101.py
recipe_urls/eatwhattonight.py
recipe_urls/elavegan.py
recipe_urls/epicurious.py
recipe_urls/errenskitchen.py
recipe_urls/ethanchlebowski.py
recipe_urls/farmhouseonboone.py
recipe_urls/fifteenspatulas.py
recipe_urls/finedininglovers.py
recipe_urls/fitmencook.py
recipe_urls/fitslowcookerqueen.py
recipe_urls/food.py
recipe_urls/food52.py
recipe_urls/foodandwine.py
recipe_urls/foodnetwork.py
recipe_urls/foodrepublic.py
recipe_urls/forksoverknives.py
recipe_urls/forktospoon.py
recipe_urls/gimmesomeoven.py
recipe_urls/gonnawantseconds.py
recipe_urls/goodfooddiscoveries.py
recipe_urls/goodhousekeeping.py
recipe_urls/greatbritishchefs.py
recipe_urls/halfbakedharvest.py
recipe_urls/handletheheat.py
recipe_urls/headbangerskitchen.py
recipe_urls/heatherchristo.py
recipe_urls/hellofresh.py
recipe_urls/hersheyland.py
recipe_urls/hostthetoast.py
recipe_urls/imworthy.py
recipe_urls-0.2.0.dist-info/LICENSE
recipe_urls-0.2.0.dist-info/METADATA
recipe_urls-0.2.0.dist-info/WHEEL
recipe_urls-0.2.0.dist-info/top_level.txt
recipe_urls-0.2.0.dist-info/RECORD
